picire/__init__.py
picire/__main__.py
picire/abstract_dd.py
picire/abstract_parallel_dd.py
picire/cli.py
picire/combined_iterator.py
picire/combined_parallel_dd.py
picire/config_iterators.py
picire/config_splitters.py
picire/dd.py
picire/outcome.py
picire/outcome_cache.py
picire/parallel_dd.py
picire/parallel_loop.py
picire/shared_cache.py
picire/subprocess_test.py
picire-21.8.dist-info/LICENSE.rst
picire-21.8.dist-info/METADATA
picire-21.8.dist-info/WHEEL
picire-21.8.dist-info/entry_points.txt
picire-21.8.dist-info/top_level.txt
picire-21.8.dist-info/RECORD
