Metadata-Version: 2.1
Name: picire
Version: 21.8
Summary: Picire Parallel Delta Debugging Framework
Home-page: https://github.com/renatahodovan/picire
Author: Renata Hodovan, Akos Kiss
Author-email: hodovan@inf.u-szeged.hu, akiss@inf.u-szeged.hu
License: BSD
Platform: any
Classifier: Intended Audience :: Developers
Classifier: License :: OSI Approved :: BSD License
Classifier: Operating System :: OS Independent
Classifier: Programming Language :: Python
Classifier: Programming Language :: Python :: 3
Classifier: Programming Language :: Python :: 3.5
Classifier: Programming Language :: Python :: 3.6
Classifier: Programming Language :: Python :: 3.7
Classifier: Programming Language :: Python :: 3.8
Classifier: Programming Language :: Python :: 3.9
Classifier: Topic :: Software Development :: Testing
Requires-Python: >=3.5
License-File: LICENSE.rst
Requires-Dist: chardet
Requires-Dist: inators
Requires-Dist: psutil
Requires-Dist: setuptools
